{
    "blocks" : {
        "bonus" : {},
        "bonus2" : {},
        "bonus3" : {},
        "bonus4" : {},
        "bonus5" : {},
        "autobonus" : {},
        "autobonus2" : {},
        "autobonus3" : {},
        "heal" : {},
        "percentheal" : {},
        "itemheal" : {},
        "skill" : {},
        "itemskill" : {},
        "unitskilluseid" : {},
        "sc_start" : {},
        "sc_start4" : {},
        "sc_end" : {},
        "getitem" : {},
        "rentitem" : {},
        "delitem" : {},
        "getrandgroupitem" : {},
        "skilleffect" : {},
        "specialeffect2" : {},
        "setfont" : {},
        "buyingstore" : {},
        "searchstores" : {},
        "set" : {},
        "input" : {},
        "announce" : {},
        "callfunc" : {},
        "end" : {},
        "warp" : {},
        "pet" : {},
        "bpet" : {},
        "mercenary_create" : {},
        "mercenary_heal" : {},
        "mercenary_sc_start" : {},
        "produce" : {},
        "cooking" : {},
        "makerune" : {},
        "guildgetexp" : {},
        "getexp" : {},
        "monster" : {},
        "homevolution" : {},
        "setoption" : {},
        "setmounting" : {},
        "setfalcon" : {},
        "getgroupitem" : {},
        "resetstatus" : {},
        "bonus_script" : {},
        "playbgm" : {},
        "transform" : {},
        "sc_start2" : {},
        "petloot" : {},
        "petrecovery" : {},
        "petskillbonus" : {},
        "petskillattack" : {},
        "petskillattack2" : {},
        "petskillsupport" : {},
        "petheal" : {},
        "for" : {},
        "getmapxy" : {},
        "specialeffect" : {},
        "showscript" : {}
    }
}
